itn/README.md
itn/__init__.py
itn/__main__.py
itn/main.py
itn/chinese/__init__.py
itn/chinese/inverse_normalizer.py
itn/chinese/rules/__init__.py
itn/chinese/rules/cardinal.py
itn/chinese/rules/char.py
itn/chinese/rules/date.py
itn/chinese/rules/fraction.py
itn/chinese/rules/license_plate.py
itn/chinese/rules/math.py
itn/chinese/rules/measure.py
itn/chinese/rules/money.py
itn/chinese/rules/postprocessor.py
itn/chinese/rules/time.py
itn/chinese/rules/whitelist.py
itn/chinese/test/__init__.py
itn/chinese/test/normalizer_test.py
itn/chinese/test/utils.py
itn/japanese/__init__.py
itn/japanese/inverse_normalizer.py
itn/japanese/rules/__init__.py
itn/japanese/rules/cardinal.py
itn/japanese/rules/char.py
itn/japanese/rules/date.py
itn/japanese/rules/fraction.py
itn/japanese/rules/math.py
itn/japanese/rules/measure.py
itn/japanese/rules/money.py
itn/japanese/rules/ordinal.py
itn/japanese/rules/postprocessor.py
itn/japanese/rules/preprocessor.py
itn/japanese/rules/time.py
itn/japanese/rules/whitelist.py
itn/japanese/test/__init__.py
itn/japanese/test/normalizer_test.py
itn/japanese/test/utils.py
text_normalizer/__init__.py
text_normalizer/normalizer.py
text_normalizer/utils.py
tn/README.md
tn/__init__.py
tn/__main__.py
tn/ja_tn_tagger.fst
tn/ja_tn_verbalizer.fst
tn/main.py
tn/processor.py
tn/token_parser.py
tn/utils.py
tn/zh_tn_tagger.fst
tn/zh_tn_verbalizer.fst
tn/chinese/__init__.py
tn/chinese/normalizer.py
tn/chinese/data/char/charset_extension.tsv
tn/chinese/data/char/charset_national_standard_2013_8105.tsv
tn/chinese/data/char/fullwidth_to_halfwidth.tsv
tn/chinese/data/char/punctuations_zh.tsv
tn/chinese/data/char/traditional_to_simple.tsv
tn/chinese/data/date/d.tsv
tn/chinese/data/date/dd.tsv
tn/chinese/data/date/m.tsv
tn/chinese/data/date/mm.tsv
tn/chinese/data/default/blacklist.tsv
tn/chinese/data/default/whitelist.tsv
tn/chinese/data/erhua/whitelist.tsv
tn/chinese/data/math/operator.tsv
tn/chinese/data/measure/units_en.tsv
tn/chinese/data/measure/units_zh.tsv
tts_text_norm-1.0.0.dist-info/METADATA
tts_text_norm-1.0.0.dist-info/WHEEL
tts_text_norm-1.0.0.dist-info/top_level.txt
tts_text_norm-1.0.0.dist-info/RECORD
